superblockify/__init__.py
superblockify/_api.py
superblockify/_version.py
superblockify/attribute.py
superblockify/cities.yml
superblockify/config.py
superblockify/graph_stats.py
superblockify/logging.cfg
superblockify/plot.py
superblockify/utils.py
superblockify/metrics/__init__.py
superblockify/metrics/distances.py
superblockify/metrics/measures.py
superblockify/metrics/metric.py
superblockify/metrics/plot.py
superblockify/partitioning/__init__.py
superblockify/partitioning/base.py
superblockify/partitioning/checks.py
superblockify/partitioning/plot.py
superblockify/partitioning/representative.py
superblockify/partitioning/speed.py
superblockify/partitioning/utils.py
superblockify/partitioning/approaches/__init__.py
superblockify/partitioning/approaches/attribute.py
superblockify/partitioning/approaches/bearing.py
superblockify/partitioning/approaches/betweenness.py
superblockify/partitioning/approaches/dummy.py
superblockify/partitioning/approaches/steiner_tree.py
superblockify/partitioning/approaches/streettype.py
superblockify/population/__init__.py
superblockify/population/approximation.py
superblockify/population/ghsl.py
superblockify/population/tessellation.py
superblockify-1.0.1.dist-info/LICENSE
superblockify-1.0.1.dist-info/METADATA
superblockify-1.0.1.dist-info/WHEEL
superblockify-1.0.1.dist-info/top_level.txt
superblockify-1.0.1.dist-info/RECORD
