Metadata-Version: 2.1
Name: superblockify
Version: 1.0.1
Summary: Automated Generation, Visualization, and Analysis of potential Superblocks in Cities
Author: Carlson Büth, Anastassia Vybornova, Michael Szell
Maintainer-email: Carlson Büth <carlson@cbueth.de>
License: APGL-3.0-or-later
Project-URL: Documentation, https://superblockify.city/
Project-URL: Repository, https://github.com/NERDSITU/superblockify
Project-URL: Changelog, https://superblockify.city/changelog/
Keywords: Low Traffic Neighborhoods,GIS,Networks,OpenStreetMap,Urban Planning,Urban Mobility,Urban Data
Classifier: Development Status :: 5 - Production/Stable
Classifier: Intended Audience :: Developers
Classifier: Intended Audience :: Science/Research
Classifier: License :: OSI Approved :: GNU Affero General Public License v3 or later (AGPLv3+)
Classifier: Operating System :: OS Independent
Classifier: Programming Language :: Python :: 3
Classifier: Programming Language :: Python :: 3 :: Only
Classifier: Programming Language :: Python :: 3.10
Classifier: Programming Language :: Python :: 3.11
Classifier: Programming Language :: Python :: 3.12
Classifier: Natural Language :: English
Classifier: Topic :: Scientific/Engineering :: GIS
Classifier: Topic :: Scientific/Engineering :: Information Analysis
Classifier: Topic :: Scientific/Engineering :: Visualization
Classifier: Topic :: Scientific/Engineering :: Physics
Requires-Python: >=3.10
License-File: LICENSE
Requires-Dist: osmnx>=1.6.0
Requires-Dist: geopandas
Requires-Dist: rasterio
Requires-Dist: shapely
Requires-Dist: numba
Requires-Dist: scipy
Requires-Dist: tqdm
Requires-Dist: contextily
Requires-Dist: ruamel.yaml
Requires-Dist: seaborn
Requires-Dist: psutil
Requires-Dist: typing-extensions
Provides-Extra: lint
Requires-Dist: blackd; extra == "lint"
Requires-Dist: isort; extra == "lint"
Requires-Dist: pylint; extra == "lint"
Provides-Extra: test
Requires-Dist: pytest; extra == "test"
Requires-Dist: pytest-cov; extra == "test"
Requires-Dist: coverage; extra == "test"
Provides-Extra: doc
Requires-Dist: sphinx; extra == "doc"
Requires-Dist: numpydoc; extra == "doc"
Requires-Dist: myst-nb; extra == "doc"
Requires-Dist: sphinx-book-theme; extra == "doc"
Requires-Dist: rasterstats; extra == "doc"
Requires-Dist: momepy; extra == "doc"
Provides-Extra: all
Requires-Dist: superblockify[doc,lint,test]; extra == "all"
